MANIFEST.in
README.md
setup.cfg
setup.py
topsis_101917140/__init__.py
topsis_101917140/topsis_101917140.py
topsis_101917140.egg-info/PKG-INFO
topsis_101917140.egg-info/SOURCES.txt
topsis_101917140.egg-info/dependency_links.txt
topsis_101917140.egg-info/entry_points.txt
topsis_101917140.egg-info/requires.txt
topsis_101917140.egg-info/top_level.txt