Metadata-Version: 2.1
Name: topsis-101917140
Version: 1.1
Summary: A Python package to rank ML models/choices using topsis technique
Home-page: https://github.com/SainaAgrawal/Topsis-101917140
Author: Saina Agarwal
Author-email: sagrawal_be19@thapar.edu
License: MIT
Platform: UNKNOWN
Classifier: License :: OSI Approved :: MIT License
Classifier: Programming Language :: Python :: 3
Classifier: Programming Language :: Python :: 3.7
